LICENSE.txt
evo_package_tunnel/__init__.py
evo_package_tunnel/automation/api.yaml
evo_package_tunnel/automation/entity.yaml
evo_package_tunnel/automation/tests.yaml
evo_package_tunnel/control/__init__.py
evo_package_tunnel/entity/__init__.py
evo_package_tunnel/utility/IuTunnel.py
evo_package_tunnel/utility/IuTunnelCloudFlare.py
evo_package_tunnel/utility/IuTunnelNGrok.py
evo_package_tunnel/utility/IuTunnelPinggy.py
evo_package_tunnel/utility/UTunnel.py
evo_package_tunnel/utility/__init__.py
evo_package_tunnel-2024.10.22328.dist-info/LICENSE.txt
evo_package_tunnel-2024.10.22328.dist-info/METADATA
evo_package_tunnel-2024.10.22328.dist-info/WHEEL
evo_package_tunnel-2024.10.22328.dist-info/RECORD
